nebula-chia/__init__.py
nebula-chia/chia.py
nebulachia/__init__.py
nebulachia/chia.py
nebulachia/convertor.py
nebula_chia-0.2.dist-info/METADATA
nebula_chia-0.2.dist-info/WHEEL
nebula_chia-0.2.dist-info/top_level.txt
nebula_chia-0.2.dist-info/RECORD
