Metadata-Version: 2.1
Name: nebula-chia
Version: 0.2
Summary: Chia Network data ETL for Nebula Graph
Home-page: https://github.com/wey-gu/nebula-chia
Author: Wey Gu
Author-email: weyl.gu@gmail.com
License: UNKNOWN
Project-URL: Bug Tracker, https://github.com/wey-gu/nebula-chia/issues
Platform: UNKNOWN
Classifier: Programming Language :: Python :: 3
Classifier: License :: OSI Approved :: Apache Software License
Classifier: Operating System :: OS Independent
Requires-Python: >=3.6
Requires-Dist: chia-blockchain
